{
  "name": "Avaros",
  "engines": [],
  "models": [
    {
      "name": "Ideal"
    },
    {
      "name": "Kickmonomatic"
    },
    {
      "name": "Kingline"
    },
    {
      "name": "Primus"
    },
    {
      "name": "Record"
    },
    {
      "name": "Super 7"
    }
  ],
  "forks": [
    {
      "name": "Super 7 Stock Forks"
    },
    {
      "name": "Record Stock Forks"
    },
    {
      "name": "Primus Stock Forks"
    },
    {
      "name": "Kingline Stock Forks"
    },
    {
      "name": "Kickmonomatic Stock Forks"
    },
    {
      "name": "Ideal Stock Forks"
    }
  ],
  "wheels": [
    {
      "name": "Super 7 Stock Wheels"
    },
    {
      "name": "Record Stock Wheels"
    },
    {
      "name": "Primus Stock Wheels"
    },
    {
      "name": "Kingline Stock Wheels"
    },
    {
      "name": "Kickmonomatic Stock Wheels"
    },
    {
      "name": "Ideal Stock Wheels"
    }
  ],
  "exhausts": [
    {
      "name": "Super 7 Stock Exhaust"
    },
    {
      "name": "Record Stock Exhaust"
    },
    {
      "name": "Primus Stock Exhaust"
    },
    {
      "name": "Kingline Stock Exhaust"
    },
    {
      "name": "Kickmonomatic Stock Exhaust"
    },
    {
      "name": "Ideal Stock Exhaust"
    }
  ],
  "clutches": [],
  "cranks": [],
  "ignitions": [],
  "pulleys": [],
  "variators": [],
  "categories": [
    "mopeds"
  ],
  "cylinders": []
}