{
  "name": "Bridgestone",
  "engines": [],
  "models": [
    {
      "name": "7"
    },
    {
      "name": "Surfrider"
    }
  ],
  "exhausts": [
    {
      "name": "Surfrider Stock Exhaust"
    },
    {
      "name": "7 Stock Exhaust"
    }
  ],
  "cylinders": [],
  "forks": [
    {
      "name": "Surfrider Stock Forks"
    },
    {
      "name": "7 Stock Forks"
    }
  ],
  "wheels": [
    {
      "name": "Surfrider Stock Wheels"
    },
    {
      "name": "7 Stock Wheels"
    }
  ],
  "categories": [
    "mopeds"
  ],
  "clutches": [],
  "cranks": [],
  "ignitions": [],
  "pulleys": [],
  "variators": []
}