{
  "name": "Motobecane",
  "engines": [],
  "categories": [
    "moped"
  ],
  "forks": [
    {
      "name": "Velosolex Stock Forks"
    },
    {
      "name": "Mobylette Stock Forks"
    },
    {
      "name": "151 Stock Forks"
    },
    {
      "name": "M3PRTS Stock Forks"
    },
    {
      "name": "99Z Stock Forks"
    },
    {
      "name": "M11 Stock Forks"
    },
    {
      "name": "41V Stock Forks"
    },
    {
      "name": "L93E Stock Forks"
    },
    {
      "name": "L99E Stock Forks"
    },
    {
      "name": "H40TS Stock Forks"
    },
    {
      "name": "92GT Stock Forks"
    },
    {
      "name": "88LC Stock Forks"
    },
    {
      "name": "51 Stock Forks"
    },
    {
      "name": "H40 Stock Forks"
    },
    {
      "name": "Mini Moby M1 PRTD Stock Forks"
    },
    {
      "name": "X1L Stock Forks"
    },
    {
      "name": "Romp Stock Forks"
    },
    {
      "name": "Mono 50 Stock Forks"
    },
    {
      "name": "M1PR Stock Forks"
    },
    {
      "name": "Sport 50 MK 2 Stock Forks"
    },
    {
      "name": "Majormatic Stock Forks"
    },
    {
      "name": "X7S Stock Forks"
    },
    {
      "name": "Sport Special Stock Forks"
    },
    {
      "name": "Duamatic Stock Forks"
    },
    {
      "name": "50L Stock Forks"
    },
    {
      "name": "H40S Stock Forks"
    },
    {
      "name": "Le Moped Stock Forks"
    },
    {
      "name": "Mastermatic Stock Forks"
    },
    {
      "name": "X7L Stock Forks"
    },
    {
      "name": "D55 Stock Forks"
    },
    {
      "name": "Moby X1 Stock Forks"
    },
    {
      "name": "50V Stock Forks"
    },
    {
      "name": "D52 Stock Forks"
    },
    {
      "name": "L94TTE Stock Forks"
    },
    {
      "name": "X1 Stock Forks"
    },
    {
      "name": "88L Stock Forks"
    },
    {
      "name": "Mobymatic Stock Forks"
    },
    {
      "name": "H50VLC Stock Forks"
    },
    {
      "name": "L99EF Stock Forks"
    },
    {
      "name": "Cady Stock Forks"
    },
    {
      "name": "TM 4 (Mokick) Stock Forks"
    },
    {
      "name": "50VLC Stock Forks"
    },
    {
      "name": "Monty Stock Forks"
    },
    {
      "name": "Traveler Stock Forks"
    },
    {
      "name": "93DL Stock Forks"
    },
    {
      "name": "40TL Stock Forks"
    },
    {
      "name": "M1 Stock Forks"
    },
    {
      "name": "40T Stock Forks"
    },
    {
      "name": "Poney 50 Stock Forks"
    },
    {
      "name": "H50LS Stock Forks"
    },
    {
      "name": "N140 TL Stock Forks"
    },
    {
      "name": "H40VLC Stock Forks"
    },
    {
      "name": "50VLX Stock Forks"
    },
    {
      "name": "881 Stock Forks"
    },
    {
      "name": "Speciale 50 Stock Forks"
    },
    {
      "name": "40TS Stock Forks"
    },
    {
      "name": "Minor Major Stock Forks"
    },
    {
      "name": "50 Stock Forks"
    },
    {
      "name": "40 Stock Forks"
    },
    {
      "name": "Mini Moby M1 PRTS Stock Forks"
    },
    {
      "name": "50VLA Stock Forks"
    },
    {
      "name": "50VL Stock Forks"
    },
    {
      "name": "SP94 Stock Forks"
    },
    {
      "name": "Moby X Stock Forks"
    },
    {
      "name": "AU 42 A Bonnie Stock Forks"
    },
    {
      "name": "51V Stock Forks"
    },
    {
      "name": "Luxamatic Stock Forks"
    },
    {
      "name": "AV51 Stock Forks"
    },
    {
      "name": "X7AVL Stock Forks"
    },
    {
      "name": "4600 (Solex) Stock Forks"
    },
    {
      "name": "50VA Stock Forks"
    },
    {
      "name": "H40TL Stock Forks"
    },
    {
      "name": "AV89MB Stock Forks"
    },
    {
      "name": "7 Stock Forks"
    },
    {
      "name": "92DL Stock Forks"
    },
    {
      "name": "SP50 Stock Forks"
    },
    {
      "name": "Moby Stock Forks"
    },
    {
      "name": "50S Stock Forks"
    },
    {
      "name": "M3PRT Stock Forks"
    },
    {
      "name": "H50S Stock Forks"
    },
    {
      "name": "Commuter Stock Forks"
    },
    {
      "name": "L92N Stock Forks"
    },
    {
      "name": "Ranger 7 Stock Forks"
    },
    {
      "name": "TLS Stock Forks"
    },
    {
      "name": "Sebring Stock Forks"
    },
    {
      "name": "M50ev Stock Forks"
    },
    {
      "name": "X7VX Stock Forks"
    },
    {
      "name": "85L Stock Forks"
    },
    {
      "name": "Monty SP Stock Forks"
    },
    {
      "name": "Majorette Stock Forks"
    }
  ],
  "wheels": [
    {
      "name": "Velosolex Stock Wheels"
    },
    {
      "name": "Mobylette Stock Wheels"
    },
    {
      "name": "151 Stock Wheels"
    },
    {
      "name": "M3PRTS Stock Wheels"
    },
    {
      "name": "99Z Stock Wheels"
    },
    {
      "name": "M11 Stock Wheels"
    },
    {
      "name": "41V Stock Wheels"
    },
    {
      "name": "L93E Stock Wheels"
    },
    {
      "name": "L99E Stock Wheels"
    },
    {
      "name": "H40TS Stock Wheels"
    },
    {
      "name": "92GT Stock Wheels"
    },
    {
      "name": "88LC Stock Wheels"
    },
    {
      "name": "51 Stock Wheels"
    },
    {
      "name": "H40 Stock Wheels"
    },
    {
      "name": "Mini Moby M1 PRTD Stock Wheels"
    },
    {
      "name": "X1L Stock Wheels"
    },
    {
      "name": "Romp Stock Wheels"
    },
    {
      "name": "Mono 50 Stock Wheels"
    },
    {
      "name": "M1PR Stock Wheels"
    },
    {
      "name": "Sport 50 MK 2 Stock Wheels"
    },
    {
      "name": "Majormatic Stock Wheels"
    },
    {
      "name": "X7S Stock Wheels"
    },
    {
      "name": "Sport Special Stock Wheels"
    },
    {
      "name": "Duamatic Stock Wheels"
    },
    {
      "name": "50L Stock Wheels"
    },
    {
      "name": "H40S Stock Wheels"
    },
    {
      "name": "Le Moped Stock Wheels"
    },
    {
      "name": "Mastermatic Stock Wheels"
    },
    {
      "name": "X7L Stock Wheels"
    },
    {
      "name": "D55 Stock Wheels"
    },
    {
      "name": "Moby X1 Stock Wheels"
    },
    {
      "name": "50V Stock Wheels"
    },
    {
      "name": "D52 Stock Wheels"
    },
    {
      "name": "L94TTE Stock Wheels"
    },
    {
      "name": "X1 Stock Wheels"
    },
    {
      "name": "88L Stock Wheels"
    },
    {
      "name": "Mobymatic Stock Wheels"
    },
    {
      "name": "H50VLC Stock Wheels"
    },
    {
      "name": "L99EF Stock Wheels"
    },
    {
      "name": "Cady Stock Wheels"
    },
    {
      "name": "TM 4 (Mokick) Stock Wheels"
    },
    {
      "name": "50VLC Stock Wheels"
    },
    {
      "name": "Monty Stock Wheels"
    },
    {
      "name": "Traveler Stock Wheels"
    },
    {
      "name": "93DL Stock Wheels"
    },
    {
      "name": "40TL Stock Wheels"
    },
    {
      "name": "M1 Stock Wheels"
    },
    {
      "name": "40T Stock Wheels"
    },
    {
      "name": "Poney 50 Stock Wheels"
    },
    {
      "name": "H50LS Stock Wheels"
    },
    {
      "name": "N140 TL Stock Wheels"
    },
    {
      "name": "H40VLC Stock Wheels"
    },
    {
      "name": "50VLX Stock Wheels"
    },
    {
      "name": "881 Stock Wheels"
    },
    {
      "name": "Speciale 50 Stock Wheels"
    },
    {
      "name": "40TS Stock Wheels"
    },
    {
      "name": "Minor Major Stock Wheels"
    },
    {
      "name": "50 Stock Wheels"
    },
    {
      "name": "40 Stock Wheels"
    },
    {
      "name": "Mini Moby M1 PRTS Stock Wheels"
    },
    {
      "name": "50VLA Stock Wheels"
    },
    {
      "name": "50VL Stock Wheels"
    },
    {
      "name": "SP94 Stock Wheels"
    },
    {
      "name": "Moby X Stock Wheels"
    },
    {
      "name": "AU 42 A Bonnie Stock Wheels"
    },
    {
      "name": "51V Stock Wheels"
    },
    {
      "name": "Luxamatic Stock Wheels"
    },
    {
      "name": "AV51 Stock Wheels"
    },
    {
      "name": "X7AVL Stock Wheels"
    },
    {
      "name": "4600 (Solex) Stock Wheels"
    },
    {
      "name": "50VA Stock Wheels"
    },
    {
      "name": "H40TL Stock Wheels"
    },
    {
      "name": "AV89MB Stock Wheels"
    },
    {
      "name": "7 Stock Wheels"
    },
    {
      "name": "92DL Stock Wheels"
    },
    {
      "name": "SP50 Stock Wheels"
    },
    {
      "name": "Moby Stock Wheels"
    },
    {
      "name": "50S Stock Wheels"
    },
    {
      "name": "M3PRT Stock Wheels"
    },
    {
      "name": "H50S Stock Wheels"
    },
    {
      "name": "Commuter Stock Wheels"
    },
    {
      "name": "L92N Stock Wheels"
    },
    {
      "name": "Ranger 7 Stock Wheels"
    },
    {
      "name": "TLS Stock Wheels"
    },
    {
      "name": "Sebring Stock Wheels"
    },
    {
      "name": "M50ev Stock Wheels"
    },
    {
      "name": "X7VX Stock Wheels"
    },
    {
      "name": "85L Stock Wheels"
    },
    {
      "name": "Monty SP Stock Wheels"
    },
    {
      "name": "Majorette Stock Wheels"
    }
  ],
  "clutches": [
    {
      "name": "Stock Clutch"
    }
  ],
  "cranks": [
    {
      "name": "Stock Crank"
    }
  ],
  "cylinders": [
    {
      "name": "Velosolex Stock Cylinder"
    },
    {
      "name": "Mobylette Stock Cylinder"
    },
    {
      "name": "151 Stock Cylinder"
    },
    {
      "name": "M3PRTS Stock Cylinder"
    },
    {
      "name": "99Z Stock Cylinder"
    },
    {
      "name": "M11 Stock Cylinder"
    },
    {
      "name": "41V Stock Cylinder"
    },
    {
      "name": "L93E Stock Cylinder"
    },
    {
      "name": "L99E Stock Cylinder"
    },
    {
      "name": "H40TS Stock Cylinder"
    },
    {
      "name": "92GT Stock Cylinder"
    },
    {
      "name": "88LC Stock Cylinder"
    },
    {
      "name": "51 Stock Cylinder"
    },
    {
      "name": "H40 Stock Cylinder"
    },
    {
      "name": "Mini Moby M1 PRTD Stock Cylinder"
    },
    {
      "name": "X1L Stock Cylinder"
    },
    {
      "name": "Romp Stock Cylinder"
    },
    {
      "name": "Mono 50 Stock Cylinder"
    },
    {
      "name": "M1PR Stock Cylinder"
    },
    {
      "name": "Sport 50 MK 2 Stock Cylinder"
    },
    {
      "name": "Majormatic Stock Cylinder"
    },
    {
      "name": "X7S Stock Cylinder"
    },
    {
      "name": "Sport Special Stock Cylinder"
    },
    {
      "name": "Duamatic Stock Cylinder"
    },
    {
      "name": "50L Stock Cylinder"
    },
    {
      "name": "H40S Stock Cylinder"
    },
    {
      "name": "Le Moped Stock Cylinder"
    },
    {
      "name": "Mastermatic Stock Cylinder"
    },
    {
      "name": "X7L Stock Cylinder"
    },
    {
      "name": "D55 Stock Cylinder"
    },
    {
      "name": "Moby X1 Stock Cylinder"
    },
    {
      "name": "50V Stock Cylinder"
    },
    {
      "name": "D52 Stock Cylinder"
    },
    {
      "name": "L94TTE Stock Cylinder"
    },
    {
      "name": "X1 Stock Cylinder"
    },
    {
      "name": "88L Stock Cylinder"
    },
    {
      "name": "Mobymatic Stock Cylinder"
    },
    {
      "name": "H50VLC Stock Cylinder"
    },
    {
      "name": "L99EF Stock Cylinder"
    },
    {
      "name": "Cady Stock Cylinder"
    },
    {
      "name": "TM 4 (Mokick) Stock Cylinder"
    },
    {
      "name": "50VLC Stock Cylinder"
    },
    {
      "name": "Monty Stock Cylinder"
    },
    {
      "name": "Traveler Stock Cylinder"
    },
    {
      "name": "93DL Stock Cylinder"
    },
    {
      "name": "40TL Stock Cylinder"
    },
    {
      "name": "M1 Stock Cylinder"
    },
    {
      "name": "40T Stock Cylinder"
    },
    {
      "name": "Poney 50 Stock Cylinder"
    },
    {
      "name": "H50LS Stock Cylinder"
    },
    {
      "name": "N140 TL Stock Cylinder"
    },
    {
      "name": "H40VLC Stock Cylinder"
    },
    {
      "name": "50VLX Stock Cylinder"
    },
    {
      "name": "881 Stock Cylinder"
    },
    {
      "name": "Speciale 50 Stock Cylinder"
    },
    {
      "name": "40TS Stock Cylinder"
    },
    {
      "name": "Minor Major Stock Cylinder"
    },
    {
      "name": "50 Stock Cylinder"
    },
    {
      "name": "40 Stock Cylinder"
    },
    {
      "name": "Mini Moby M1 PRTS Stock Cylinder"
    },
    {
      "name": "50VLA Stock Cylinder"
    },
    {
      "name": "50VL Stock Cylinder"
    },
    {
      "name": "SP94 Stock Cylinder"
    },
    {
      "name": "Moby X Stock Cylinder"
    },
    {
      "name": "AU 42 A Bonnie Stock Cylinder"
    },
    {
      "name": "51V Stock Cylinder"
    },
    {
      "name": "Luxamatic Stock Cylinder"
    },
    {
      "name": "AV51 Stock Cylinder"
    },
    {
      "name": "X7AVL Stock Cylinder"
    },
    {
      "name": "4600 (Solex) Stock Cylinder"
    },
    {
      "name": "50VA Stock Cylinder"
    },
    {
      "name": "H40TL Stock Cylinder"
    },
    {
      "name": "AV89MB Stock Cylinder"
    },
    {
      "name": "7 Stock Cylinder"
    },
    {
      "name": "92DL Stock Cylinder"
    },
    {
      "name": "SP50 Stock Cylinder"
    },
    {
      "name": "Moby Stock Cylinder"
    },
    {
      "name": "50S Stock Cylinder"
    },
    {
      "name": "M3PRT Stock Cylinder"
    },
    {
      "name": "H50S Stock Cylinder"
    },
    {
      "name": "Commuter Stock Cylinder"
    },
    {
      "name": "L92N Stock Cylinder"
    },
    {
      "name": "Ranger 7 Stock Cylinder"
    },
    {
      "name": "TLS Stock Cylinder"
    },
    {
      "name": "Sebring Stock Cylinder"
    },
    {
      "name": "M50ev Stock Cylinder"
    },
    {
      "name": "X7VX Stock Cylinder"
    },
    {
      "name": "85L Stock Cylinder"
    },
    {
      "name": "Monty SP Stock Cylinder"
    },
    {
      "name": "Majorette Stock Cylinder"
    }
  ],
  "exhausts": [
    {
      "name": "Velosolex Stock Exhaust"
    },
    {
      "name": "Mobylette Stock Exhaust"
    },
    {
      "name": "151 Stock Exhaust"
    },
    {
      "name": "M3PRTS Stock Exhaust"
    },
    {
      "name": "99Z Stock Exhaust"
    },
    {
      "name": "M11 Stock Exhaust"
    },
    {
      "name": "41V Stock Exhaust"
    },
    {
      "name": "L93E Stock Exhaust"
    },
    {
      "name": "L99E Stock Exhaust"
    },
    {
      "name": "H40TS Stock Exhaust"
    },
    {
      "name": "92GT Stock Exhaust"
    },
    {
      "name": "88LC Stock Exhaust"
    },
    {
      "name": "51 Stock Exhaust"
    },
    {
      "name": "H40 Stock Exhaust"
    },
    {
      "name": "Mini Moby M1 PRTD Stock Exhaust"
    },
    {
      "name": "X1L Stock Exhaust"
    },
    {
      "name": "Romp Stock Exhaust"
    },
    {
      "name": "Mono 50 Stock Exhaust"
    },
    {
      "name": "M1PR Stock Exhaust"
    },
    {
      "name": "Sport 50 MK 2 Stock Exhaust"
    },
    {
      "name": "Majormatic Stock Exhaust"
    },
    {
      "name": "X7S Stock Exhaust"
    },
    {
      "name": "Sport Special Stock Exhaust"
    },
    {
      "name": "Duamatic Stock Exhaust"
    },
    {
      "name": "50L Stock Exhaust"
    },
    {
      "name": "H40S Stock Exhaust"
    },
    {
      "name": "Le Moped Stock Exhaust"
    },
    {
      "name": "Mastermatic Stock Exhaust"
    },
    {
      "name": "X7L Stock Exhaust"
    },
    {
      "name": "D55 Stock Exhaust"
    },
    {
      "name": "Moby X1 Stock Exhaust"
    },
    {
      "name": "50V Stock Exhaust"
    },
    {
      "name": "D52 Stock Exhaust"
    },
    {
      "name": "L94TTE Stock Exhaust"
    },
    {
      "name": "X1 Stock Exhaust"
    },
    {
      "name": "88L Stock Exhaust"
    },
    {
      "name": "Mobymatic Stock Exhaust"
    },
    {
      "name": "H50VLC Stock Exhaust"
    },
    {
      "name": "L99EF Stock Exhaust"
    },
    {
      "name": "Cady Stock Exhaust"
    },
    {
      "name": "TM 4 (Mokick) Stock Exhaust"
    },
    {
      "name": "50VLC Stock Exhaust"
    },
    {
      "name": "Monty Stock Exhaust"
    },
    {
      "name": "Traveler Stock Exhaust"
    },
    {
      "name": "93DL Stock Exhaust"
    },
    {
      "name": "40TL Stock Exhaust"
    },
    {
      "name": "M1 Stock Exhaust"
    },
    {
      "name": "40T Stock Exhaust"
    },
    {
      "name": "Poney 50 Stock Exhaust"
    },
    {
      "name": "H50LS Stock Exhaust"
    },
    {
      "name": "N140 TL Stock Exhaust"
    },
    {
      "name": "H40VLC Stock Exhaust"
    },
    {
      "name": "50VLX Stock Exhaust"
    },
    {
      "name": "881 Stock Exhaust"
    },
    {
      "name": "Speciale 50 Stock Exhaust"
    },
    {
      "name": "40TS Stock Exhaust"
    },
    {
      "name": "Minor Major Stock Exhaust"
    },
    {
      "name": "50 Stock Exhaust"
    },
    {
      "name": "40 Stock Exhaust"
    },
    {
      "name": "Mini Moby M1 PRTS Stock Exhaust"
    },
    {
      "name": "50VLA Stock Exhaust"
    },
    {
      "name": "50VL Stock Exhaust"
    },
    {
      "name": "SP94 Stock Exhaust"
    },
    {
      "name": "Moby X Stock Exhaust"
    },
    {
      "name": "AU 42 A Bonnie Stock Exhaust"
    },
    {
      "name": "51V Stock Exhaust"
    },
    {
      "name": "Luxamatic Stock Exhaust"
    },
    {
      "name": "AV51 Stock Exhaust"
    },
    {
      "name": "X7AVL Stock Exhaust"
    },
    {
      "name": "4600 (Solex) Stock Exhaust"
    },
    {
      "name": "50VA Stock Exhaust"
    },
    {
      "name": "H40TL Stock Exhaust"
    },
    {
      "name": "AV89MB Stock Exhaust"
    },
    {
      "name": "7 Stock Exhaust"
    },
    {
      "name": "92DL Stock Exhaust"
    },
    {
      "name": "SP50 Stock Exhaust"
    },
    {
      "name": "Moby Stock Exhaust"
    },
    {
      "name": "50S Stock Exhaust"
    },
    {
      "name": "M3PRT Stock Exhaust"
    },
    {
      "name": "H50S Stock Exhaust"
    },
    {
      "name": "Commuter Stock Exhaust"
    },
    {
      "name": "L92N Stock Exhaust"
    },
    {
      "name": "Ranger 7 Stock Exhaust"
    },
    {
      "name": "TLS Stock Exhaust"
    },
    {
      "name": "Sebring Stock Exhaust"
    },
    {
      "name": "M50ev Stock Exhaust"
    },
    {
      "name": "X7VX Stock Exhaust"
    },
    {
      "name": "85L Stock Exhaust"
    },
    {
      "name": "Monty SP Stock Exhaust"
    },
    {
      "name": "Majorette Stock Exhaust"
    }
  ],
  "ignitions": [
    {
      "name": "Stock Ignition"
    }
  ],
  "models": [
    {
      "name": "Majorette"
    },
    {
      "name": "Monty SP"
    },
    {
      "name": "85L"
    },
    {
      "name": "X7VX"
    },
    {
      "name": "M50ev"
    },
    {
      "name": "Sebring"
    },
    {
      "name": "TLS"
    },
    {
      "name": "Ranger 7"
    },
    {
      "name": "L92N"
    },
    {
      "name": "Commuter"
    },
    {
      "name": "H50S"
    },
    {
      "name": "M3PRT"
    },
    {
      "name": "50S"
    },
    {
      "name": "Moby"
    },
    {
      "name": "SP50"
    },
    {
      "name": "92DL"
    },
    {
      "name": "7"
    },
    {
      "name": "AV89MB"
    },
    {
      "name": "H40TL"
    },
    {
      "name": "50VA"
    },
    {
      "name": "4600 (Solex)"
    },
    {
      "name": "X7AVL"
    },
    {
      "name": "AV51"
    },
    {
      "name": "Luxamatic"
    },
    {
      "name": "51V"
    },
    {
      "name": "AU 42 A Bonnie"
    },
    {
      "name": "Moby X"
    },
    {
      "name": "SP94"
    },
    {
      "name": "50VL"
    },
    {
      "name": "50VLA"
    },
    {
      "name": "Mini Moby M1 PRTS"
    },
    {
      "name": "40"
    },
    {
      "name": "50"
    },
    {
      "name": "Minor Major"
    },
    {
      "name": "40TS"
    },
    {
      "name": "Speciale 50"
    },
    {
      "name": "881"
    },
    {
      "name": "50VLX"
    },
    {
      "name": "H40VLC"
    },
    {
      "name": "N140 TL"
    },
    {
      "name": "H50LS"
    },
    {
      "name": "Poney 50"
    },
    {
      "name": "40T"
    },
    {
      "name": "M1"
    },
    {
      "name": "40TL"
    },
    {
      "name": "93DL"
    },
    {
      "name": "Traveler"
    },
    {
      "name": "Monty"
    },
    {
      "name": "50VLC"
    },
    {
      "name": "TM 4 (Mokick)"
    },
    {
      "name": "Cady"
    },
    {
      "name": "L99EF"
    },
    {
      "name": "H50VLC"
    },
    {
      "name": "Mobymatic"
    },
    {
      "name": "88L"
    },
    {
      "name": "X1"
    },
    {
      "name": "L94TTE"
    },
    {
      "name": "D52"
    },
    {
      "name": "50V"
    },
    {
      "name": "Moby X1"
    },
    {
      "name": "D55"
    },
    {
      "name": "X7L"
    },
    {
      "name": "Mastermatic"
    },
    {
      "name": "Le Moped"
    },
    {
      "name": "H40S"
    },
    {
      "name": "50L"
    },
    {
      "name": "Duamatic"
    },
    {
      "name": "Sport Special"
    },
    {
      "name": "X7S"
    },
    {
      "name": "Majormatic"
    },
    {
      "name": "Sport 50 MK 2"
    },
    {
      "name": "M1PR"
    },
    {
      "name": "Mono 50"
    },
    {
      "name": "Romp"
    },
    {
      "name": "X1L"
    },
    {
      "name": "Mini Moby M1 PRTD"
    },
    {
      "name": "H40"
    },
    {
      "name": "51"
    },
    {
      "name": "88LC"
    },
    {
      "name": "92GT"
    },
    {
      "name": "H40TS"
    },
    {
      "name": "L99E"
    },
    {
      "name": "L93E"
    },
    {
      "name": "41V"
    },
    {
      "name": "M11"
    },
    {
      "name": "99Z"
    },
    {
      "name": "M3PRTS"
    },
    {
      "name": "151"
    },
    {
      "name": "Mobylette"
    },
    {
      "name": "Velosolex"
    }
  ],
  "pulleys": [],
  "variators": []
}