{
  "name": "Rizzato Califfo",
  "category": "moped",
  "engines": [],
  "exhausts": [
    {
      "name": "Zum 3 Stock Exhaust"
    },
    {
      "name": "Ringo Turismo Stock Exhaust"
    },
    {
      "name": "Mini Califfo K Stock Exhaust"
    },
    {
      "name": "Cross 6V Stock Exhaust"
    },
    {
      "name": "Cross 4V Stock Exhaust"
    },
    {
      "name": "Califfone Daytona Stock Exhaust"
    },
    {
      "name": "Califfo Super Stock Exhaust"
    },
    {
      "name": "Califfo Matic Stock Exhaust"
    },
    {
      "name": "Califfo Deluxe Stock Exhaust"
    },
    {
      "name": "Califfo 3-Wheeler Stock Exhaust"
    },
    {
      "name": "Califfo 2-Speed Stock Exhaust"
    },
    {
      "name": "Califfo Stock Exhaust"
    }
  ],
  "forks": [
    {
      "name": "Zum 3 Stock Forks"
    },
    {
      "name": "Ringo Turismo Stock Forks"
    },
    {
      "name": "Mini Califfo K Stock Forks"
    },
    {
      "name": "Cross 6V Stock Forks"
    },
    {
      "name": "Cross 4V Stock Forks"
    },
    {
      "name": "Califfone Daytona Stock Forks"
    },
    {
      "name": "Califfo Super Stock Forks"
    },
    {
      "name": "Califfo Matic Stock Forks"
    },
    {
      "name": "Califfo Deluxe Stock Forks"
    },
    {
      "name": "Califfo 3-Wheeler Stock Forks"
    },
    {
      "name": "Califfo 2-Speed Stock Forks"
    },
    {
      "name": "Califfo Stock Forks"
    }
  ],
  "wheels": [
    {
      "name": "Zum 3 Stock Wheels"
    },
    {
      "name": "Ringo Turismo Stock Wheels"
    },
    {
      "name": "Mini Califfo K Stock Wheels"
    },
    {
      "name": "Cross 6V Stock Wheels"
    },
    {
      "name": "Cross 4V Stock Wheels"
    },
    {
      "name": "Califfone Daytona Stock Wheels"
    },
    {
      "name": "Califfo Super Stock Wheels"
    },
    {
      "name": "Califfo Matic Stock Wheels"
    },
    {
      "name": "Califfo Deluxe Stock Wheels"
    },
    {
      "name": "Califfo 3-Wheeler Stock Wheels"
    },
    {
      "name": "Califfo 2-Speed Stock Wheels"
    },
    {
      "name": "Califfo Stock Wheels"
    }
  ],
  "cylinders": [
    {
      "name": "Zum 3 Stock Cylinder"
    },
    {
      "name": "Ringo Turismo Stock Cylinder"
    },
    {
      "name": "Mini Califfo K Stock Cylinder"
    },
    {
      "name": "Cross 6V Stock Cylinder"
    },
    {
      "name": "Cross 4V Stock Cylinder"
    },
    {
      "name": "Califfone Daytona Stock Cylinder"
    },
    {
      "name": "Califfo Super Stock Cylinder"
    },
    {
      "name": "Califfo Matic Stock Cylinder"
    },
    {
      "name": "Califfo Deluxe Stock Cylinder"
    },
    {
      "name": "Califfo 3-Wheeler Stock Cylinder"
    },
    {
      "name": "Califfo 2-Speed Stock Cylinder"
    },
    {
      "name": "Califfo Stock Cylinder"
    }
  ],
  "clutches": [
    {
      "name": "Stock Clutch"
    }
  ],
  "cranks": [
    {
      "name": "Stock Crank"
    }
  ],
  "ignitions": [
    {
      "name": "Stock Ignition"
    }
  ],
  "models": [
    {
      "name": "Califfo"
    },
    {
      "name": "Califfo 2-Speed"
    },
    {
      "name": "Califfo 3-Wheeler"
    },
    {
      "name": "Califfo Deluxe"
    },
    {
      "name": "Califfo Matic"
    },
    {
      "name": "Califfo Super"
    },
    {
      "name": "Califfone Daytona"
    },
    {
      "name": "Cross 4V"
    },
    {
      "name": "Cross 6V"
    },
    {
      "name": "Mini Califfo K"
    },
    {
      "name": "Ringo Turismo"
    },
    {
      "name": "Zum 3"
    }
  ],
  "pulleys": [],
  "variators": []
}